<annotation>
	<folder>data_fung_done</folder>
	<filename>001559.jpeg</filename>
	<path>/home/xin/Desktop/2021Spring/Peer_data/data_fung_done/001559.jpeg</path>
	<source>
		<database>Unknown</database>
	</source>
	<size>
		<width>224</width>
		<height>224</height>
		<depth>3</depth>
	</size>
	<segmented>0</segmented>
	<object>
		<name>crack</name>
		<pose>Unspecified</pose>
		<truncated>0</truncated>
		<difficult>0</difficult>
		<bndbox>
			<xmin>85</xmin>
			<ymin>96</ymin>
			<xmax>177</xmax>
			<ymax>113</ymax>
		</bndbox>
	</object>
	<object>
		<name>crack</name>
		<pose>Unspecified</pose>
		<truncated>1</truncated>
		<difficult>0</difficult>
		<bndbox>
			<xmin>86</xmin>
			<ymin>1</ymin>
			<xmax>177</xmax>
			<ymax>23</ymax>
		</bndbox>
	</object>
</annotation>
